Workbook

Sheet Heatmap
A1: Sector Non-Financial Risk Heatmap
A2: Inherent exposure, as of 28 Oct 2026. Basis: public information and expert judgement. Ratings link to the Evaluation sheet; edit them there.
J3: Helper scores (1 = Low ... 5 = Critical) used by the Overall formula
A4: No. | B4: Sector / Scope | C4: Fraud | D4: Cyber / ICT | E4: Operational Resilience | F4: TPRM | G4: Governance / Operating Model | H4: Overall | J4: Score: Fraud | K4: Score: Cyber / ICT | L4: Score: Operational Resilience | M4: Score: TPRM | N4: Score: Governance / Operating Model
A5: 1 | B5: =Evaluation!B2 -> Securitization – entire scope | C5: =Evaluation!E2 -> Very High | D5: =Evaluation!E3 -> Medium | E5: =Evaluation!E4 -> High | F5: =Evaluation!E5 -> Very High | G5: =Evaluation!E6 -> High | H5: =INDEX('Rating Scale'!$A$2:$A$6,MAX(ROUND(AVERAGE(J5:N5),0),MAX(J5:N5)-1)) -> High | J5: =MATCH(C5,'Rating Scale'!$A$2:$A$6,0) -> 4 | K5: =MATCH(D5,'Rating Scale'!$A$2:$A$6,0) -> 2 | L5: =MATCH(E5,'Rating Scale'!$A$2:$A$6,0) -> 3 | M5: =MATCH(F5,'Rating Scale'!$A$2:$A$6,0) -> 4 | N5: =MATCH(G5,'Rating Scale'!$A$2:$A$6,0) -> 3
A6: 2 | B6: =Evaluation!B7 -> Supply Chain facilities | C6: =Evaluation!E7 -> Critical | D6: =Evaluation!E8 -> High | E6: =Evaluation!E9 -> High | F6: =Evaluation!E10 -> Very High | G6: =Evaluation!E11 -> High | H6: =INDEX('Rating Scale'!$A$2:$A$6,MAX(ROUND(AVERAGE(J6:N6),0),MAX(J6:N6)-1)) -> Very High | J6: =MATCH(C6,'Rating Scale'!$A$2:$A$6,0) -> 5 | K6: =MATCH(D6,'Rating Scale'!$A$2:$A$6,0) -> 3 | L6: =MATCH(E6,'Rating Scale'!$A$2:$A$6,0) -> 3 | M6: =MATCH(F6,'Rating Scale'!$A$2:$A$6,0) -> 4 | N6: =MATCH(G6,'Rating Scale'!$A$2:$A$6,0) -> 3
A7: 3 | B7: =Evaluation!B12 -> Growth Solutions clients | C7: =Evaluation!E12 -> High | D7: =Evaluation!E13 -> High | E7: =Evaluation!E14 -> High | F7: =Evaluation!E15 -> High | G7: =Evaluation!E16 -> Very High | H7: =INDEX('Rating Scale'!$A$2:$A$6,MAX(ROUND(AVERAGE(J7:N7),0),MAX(J7:N7)-1)) -> High | J7: =MATCH(C7,'Rating Scale'!$A$2:$A$6,0) -> 3 | K7: =MATCH(D7,'Rating Scale'!$A$2:$A$6,0) -> 3 | L7: =MATCH(E7,'Rating Scale'!$A$2:$A$6,0) -> 3 | M7: =MATCH(F7,'Rating Scale'!$A$2:$A$6,0) -> 3 | N7: =MATCH(G7,'Rating Scale'!$A$2:$A$6,0) -> 4
A8: 4 | B8: =Evaluation!B17 -> Information technologies (Digital infrastructure / Data centres) | C8: =Evaluation!E17 -> Medium | D8: =Evaluation!E18 -> Critical | E8: =Evaluation!E19 -> Very High | F8: =Evaluation!E20 -> Very High | G8: =Evaluation!E21 -> Medium | H8: =INDEX('Rating Scale'!$A$2:$A$6,MAX(ROUND(AVERAGE(J8:N8),0),MAX(J8:N8)-1)) -> Very High | J8: =MATCH(C8,'Rating Scale'!$A$2:$A$6,0) -> 2 | K8: =MATCH(D8,'Rating Scale'!$A$2:$A$6,0) -> 5 | L8: =MATCH(E8,'Rating Scale'!$A$2:$A$6,0) -> 4 | M8: =MATCH(F8,'Rating Scale'!$A$2:$A$6,0) -> 4 | N8: =MATCH(G8,'Rating Scale'!$A$2:$A$6,0) -> 2
A9: 5 | B9: =Evaluation!B22 -> Communications Services (Telecom) | C9: =Evaluation!E22 -> High | D9: =Evaluation!E23 -> Critical | E9: =Evaluation!E24 -> Very High | F9: =Evaluation!E25 -> High | G9: =Evaluation!E26 -> Medium | H9: =INDEX('Rating Scale'!$A$2:$A$6,MAX(ROUND(AVERAGE(J9:N9),0),MAX(J9:N9)-1)) -> Very High | J9: =MATCH(C9,'Rating Scale'!$A$2:$A$6,0) -> 3 | K9: =MATCH(D9,'Rating Scale'!$A$2:$A$6,0) -> 5 | L9: =MATCH(E9,'Rating Scale'!$A$2:$A$6,0) -> 4 | M9: =MATCH(F9,'Rating Scale'!$A$2:$A$6,0) -> 3 | N9: =MATCH(G9,'Rating Scale'!$A$2:$A$6,0) -> 2
A10: 6 | B10: =Evaluation!B27 -> Utilities (Electricity, Gas, Water, etc.) | C10: =Evaluation!E27 -> Medium | D10: =Evaluation!E28 -> Very High | E10: =Evaluation!E29 -> Very High | F10: =Evaluation!E30 -> High | G10: =Evaluation!E31 -> Medium | H10: =INDEX('Rating Scale'!$A$2:$A$6,MAX(ROUND(AVERAGE(J10:N10),0),MAX(J10:N10)-1)) -> High | J10: =MATCH(C10,'Rating Scale'!$A$2:$A$6,0) -> 2 | K10: =MATCH(D10,'Rating Scale'!$A$2:$A$6,0) -> 4 | L10: =MATCH(E10,'Rating Scale'!$A$2:$A$6,0) -> 4 | M10: =MATCH(F10,'Rating Scale'!$A$2:$A$6,0) -> 3 | N10: =MATCH(G10,'Rating Scale'!$A$2:$A$6,0) -> 2
A11: 7 | B11: =Evaluation!B32 -> Retail Trade | C11: =Evaluation!E32 -> High | D11: =Evaluation!E33 -> Very High | E11: =Evaluation!E34 -> High | F11: =Evaluation!E35 -> High | G11: =Evaluation!E36 -> Medium | H11: =INDEX('Rating Scale'!$A$2:$A$6,MAX(ROUND(AVERAGE(J11:N11),0),MAX(J11:N11)-1)) -> High | J11: =MATCH(C11,'Rating Scale'!$A$2:$A$6,0) -> 3 | K11: =MATCH(D11,'Rating Scale'!$A$2:$A$6,0) -> 4 | L11: =MATCH(E11,'Rating Scale'!$A$2:$A$6,0) -> 3 | M11: =MATCH(F11,'Rating Scale'!$A$2:$A$6,0) -> 3 | N11: =MATCH(G11,'Rating Scale'!$A$2:$A$6,0) -> 2
A12: 8 | B12: =Evaluation!B37 -> Wholesale Trade | C12: =Evaluation!E37 -> Very High | D12: =Evaluation!E38 -> Medium | E12: =Evaluation!E39 -> Medium | F12: =Evaluation!E40 -> High | G12: =Evaluation!E41 -> Medium | H12: =INDEX('Rating Scale'!$A$2:$A$6,MAX(ROUND(AVERAGE(J12:N12),0),MAX(J12:N12)-1)) -> High | J12: =MATCH(C12,'Rating Scale'!$A$2:$A$6,0) -> 4 | K12: =MATCH(D12,'Rating Scale'!$A$2:$A$6,0) -> 2 | L12: =MATCH(E12,'Rating Scale'!$A$2:$A$6,0) -> 2 | M12: =MATCH(F12,'Rating Scale'!$A$2:$A$6,0) -> 3 | N12: =MATCH(G12,'Rating Scale'!$A$2:$A$6,0) -> 2
A13: 9 | B13: =Evaluation!B42 -> Media & Cultural Services | C13: =Evaluation!E42 -> Medium | D13: =Evaluation!E43 -> High | E13: =Evaluation!E44 -> Medium | F13: =Evaluation!E45 -> Medium | G13: =Evaluation!E46 -> Medium | H13: =INDEX('Rating Scale'!$A$2:$A$6,MAX(ROUND(AVERAGE(J13:N13),0),MAX(J13:N13)-1)) -> Medium | J13: =MATCH(C13,'Rating Scale'!$A$2:$A$6,0) -> 2 | K13: =MATCH(D13,'Rating Scale'!$A$2:$A$6,0) -> 3 | L13: =MATCH(E13,'Rating Scale'!$A$2:$A$6,0) -> 2 | M13: =MATCH(F13,'Rating Scale'!$A$2:$A$6,0) -> 2 | N13: =MATCH(G13,'Rating Scale'!$A$2:$A$6,0) -> 2
A14: 10 | B14: =Evaluation!B47 -> Automotive | C14: =Evaluation!E47 -> High | D14: =Evaluation!E48 -> Very High | E14: =Evaluation!E49 -> Very High | F14: =Evaluation!E50 -> Very High | G14: =Evaluation!E51 -> High | H14: =INDEX('Rating Scale'!$A$2:$A$6,MAX(ROUND(AVERAGE(J14:N14),0),MAX(J14:N14)-1)) -> Very High | J14: =MATCH(C14,'Rating Scale'!$A$2:$A$6,0) -> 3 | K14: =MATCH(D14,'Rating Scale'!$A$2:$A$6,0) -> 4 | L14: =MATCH(E14,'Rating Scale'!$A$2:$A$6,0) -> 4 | M14: =MATCH(F14,'Rating Scale'!$A$2:$A$6,0) -> 4 | N14: =MATCH(G14,'Rating Scale'!$A$2:$A$6,0) -> 3
A15: 11 | B15: =Evaluation!B52 -> Energy excl. Electricity | C15: =Evaluation!E52 -> High | D15: =Evaluation!E53 -> Very High | E15: =Evaluation!E54 -> High | F15: =Evaluation!E55 -> High | G15: =Evaluation!E56 -> High | H15: =INDEX('Rating Scale'!$A$2:$A$6,MAX(ROUND(AVERAGE(J15:N15),0),MAX(J15:N15)-1)) -> High | J15: =MATCH(C15,'Rating Scale'!$A$2:$A$6,0) -> 3 | K15: =MATCH(D15,'Rating Scale'!$A$2:$A$6,0) -> 4 | L15: =MATCH(E15,'Rating Scale'!$A$2:$A$6,0) -> 3 | M15: =MATCH(F15,'Rating Scale'!$A$2:$A$6,0) -> 3 | N15: =MATCH(G15,'Rating Scale'!$A$2:$A$6,0) -> 3
A16: 12 | B16: =Evaluation!B57 -> Transport & Storage | C16: =Evaluation!E57 -> Medium | D16: =Evaluation!E58 -> Very High | E16: =Evaluation!E59 -> Very High | F16: =Evaluation!E60 -> Very High | G16: =Evaluation!E61 -> Medium | H16: =INDEX('Rating Scale'!$A$2:$A$6,MAX(ROUND(AVERAGE(J16:N16),0),MAX(J16:N16)-1)) -> High | J16: =MATCH(C16,'Rating Scale'!$A$2:$A$6,0) -> 2 | K16: =MATCH(D16,'Rating Scale'!$A$2:$A$6,0) -> 4 | L16: =MATCH(E16,'Rating Scale'!$A$2:$A$6,0) -> 4 | M16: =MATCH(F16,'Rating Scale'!$A$2:$A$6,0) -> 4 | N16: =MATCH(G16,'Rating Scale'!$A$2:$A$6,0) -> 2
A17: 13 | B17: =Evaluation!B62 -> Healthcare & Pharmaceuticals | C17: =Evaluation!E62 -> High | D17: =Evaluation!E63 -> Critical | E17: =Evaluation!E64 -> Very High | F17: =Evaluation!E65 -> Very High | G17: =Evaluation!E66 -> High | H17: =INDEX('Rating Scale'!$A$2:$A$6,MAX(ROUND(AVERAGE(J17:N17),0),MAX(J17:N17)-1)) -> Very High | J17: =MATCH(C17,'Rating Scale'!$A$2:$A$6,0) -> 3 | K17: =MATCH(D17,'Rating Scale'!$A$2:$A$6,0) -> 5 | L17: =MATCH(E17,'Rating Scale'!$A$2:$A$6,0) -> 4 | M17: =MATCH(F17,'Rating Scale'!$A$2:$A$6,0) -> 4 | N17: =MATCH(G17,'Rating Scale'!$A$2:$A$6,0) -> 3
A18: 14 | B18: =Evaluation!B67 -> Chemicals excl. Pharmaceuticals | C18: =Evaluation!E67 -> Medium | D18: =Evaluation!E68 -> High | E18: =Evaluation!E69 -> High | F18: =Evaluation!E70 -> High | G18: =Evaluation!E71 -> Medium | H18: =INDEX('Rating Scale'!$A$2:$A$6,MAX(ROUND(AVERAGE(J18:N18),0),MAX(J18:N18)-1)) -> High | J18: =MATCH(C18,'Rating Scale'!$A$2:$A$6,0) -> 2 | K18: =MATCH(D18,'Rating Scale'!$A$2:$A$6,0) -> 3 | L18: =MATCH(E18,'Rating Scale'!$A$2:$A$6,0) -> 3 | M18: =MATCH(F18,'Rating Scale'!$A$2:$A$6,0) -> 3 | N18: =MATCH(G18,'Rating Scale'!$A$2:$A$6,0) -> 2
A19: 15 | B19: =Evaluation!B72 -> Real Estate | C19: =Evaluation!E72 -> High | D19: =Evaluation!E73 -> Medium | E19: =Evaluation!E74 -> Medium | F19: =Evaluation!E75 -> Medium | G19: =Evaluation!E76 -> High | H19: =INDEX('Rating Scale'!$A$2:$A$6,MAX(ROUND(AVERAGE(J19:N19),0),MAX(J19:N19)-1)) -> Medium | J19: =MATCH(C19,'Rating Scale'!$A$2:$A$6,0) -> 3 | K19: =MATCH(D19,'Rating Scale'!$A$2:$A$6,0) -> 2 | L19: =MATCH(E19,'Rating Scale'!$A$2:$A$6,0) -> 2 | M19: =MATCH(F19,'Rating Scale'!$A$2:$A$6,0) -> 2 | N19: =MATCH(G19,'Rating Scale'!$A$2:$A$6,0) -> 3
A20: 16 | B20: =Evaluation!B77 -> Equipments excl. IT | C20: =Evaluation!E77 -> Medium | D20: =Evaluation!E78 -> High | E20: =Evaluation!E79 -> High | F20: =Evaluation!E80 -> High | G20: =Evaluation!E81 -> Medium | H20: =INDEX('Rating Scale'!$A$2:$A$6,MAX(ROUND(AVERAGE(J20:N20),0),MAX(J20:N20)-1)) -> High | J20: =MATCH(C20,'Rating Scale'!$A$2:$A$6,0) -> 2 | K20: =MATCH(D20,'Rating Scale'!$A$2:$A$6,0) -> 3 | L20: =MATCH(E20,'Rating Scale'!$A$2:$A$6,0) -> 3 | M20: =MATCH(F20,'Rating Scale'!$A$2:$A$6,0) -> 3 | N20: =MATCH(G20,'Rating Scale'!$A$2:$A$6,0) -> 2
A21: 17 | B21: =Evaluation!B82 -> Materials & Ores | C21: =Evaluation!E82 -> High | D21: =Evaluation!E83 -> High | E21: =Evaluation!E84 -> High | F21: =Evaluation!E85 -> High | G21: =Evaluation!E86 -> High | H21: =INDEX('Rating Scale'!$A$2:$A$6,MAX(ROUND(AVERAGE(J21:N21),0),MAX(J21:N21)-1)) -> High | J21: =MATCH(C21,'Rating Scale'!$A$2:$A$6,0) -> 3 | K21: =MATCH(D21,'Rating Scale'!$A$2:$A$6,0) -> 3 | L21: =MATCH(E21,'Rating Scale'!$A$2:$A$6,0) -> 3 | M21: =MATCH(F21,'Rating Scale'!$A$2:$A$6,0) -> 3 | N21: =MATCH(G21,'Rating Scale'!$A$2:$A$6,0) -> 3
A22: 18 | B22: =Evaluation!B87 -> Agriculture, Food, Tobacco | C22: =Evaluation!E87 -> High | D22: =Evaluation!E88 -> High | E22: =Evaluation!E89 -> High | F22: =Evaluation!E90 -> High | G22: =Evaluation!E91 -> Medium | H22: =INDEX('Rating Scale'!$A$2:$A$6,MAX(ROUND(AVERAGE(J22:N22),0),MAX(J22:N22)-1)) -> High | J22: =MATCH(C22,'Rating Scale'!$A$2:$A$6,0) -> 3 | K22: =MATCH(D22,'Rating Scale'!$A$2:$A$6,0) -> 3 | L22: =MATCH(E22,'Rating Scale'!$A$2:$A$6,0) -> 3 | M22: =MATCH(F22,'Rating Scale'!$A$2:$A$6,0) -> 3 | N22: =MATCH(G22,'Rating Scale'!$A$2:$A$6,0) -> 2
A23: 19 | B23: =Evaluation!B92 -> Building & Public Works | C23: =Evaluation!E92 -> Very High | D23: =Evaluation!E93 -> Medium | E23: =Evaluation!E94 -> High | F23: =Evaluation!E95 -> Very High | G23: =Evaluation!E96 -> High | H23: =INDEX('Rating Scale'!$A$2:$A$6,MAX(ROUND(AVERAGE(J23:N23),0),MAX(J23:N23)-1)) -> High | J23: =MATCH(C23,'Rating Scale'!$A$2:$A$6,0) -> 4 | K23: =MATCH(D23,'Rating Scale'!$A$2:$A$6,0) -> 2 | L23: =MATCH(E23,'Rating Scale'!$A$2:$A$6,0) -> 3 | M23: =MATCH(F23,'Rating Scale'!$A$2:$A$6,0) -> 4 | N23: =MATCH(G23,'Rating Scale'!$A$2:$A$6,0) -> 3
A24: 20 | B24: =Evaluation!B97 -> Hotels, Tourism, Leisure | C24: =Evaluation!E97 -> Medium | D24: =Evaluation!E98 -> High | E24: =Evaluation!E99 -> Medium | F24: =Evaluation!E100 -> High | G24: =Evaluation!E101 -> Medium | H24: =INDEX('Rating Scale'!$A$2:$A$6,MAX(ROUND(AVERAGE(J24:N24),0),MAX(J24:N24)-1)) -> Medium | J24: =MATCH(C24,'Rating Scale'!$A$2:$A$6,0) -> 2 | K24: =MATCH(D24,'Rating Scale'!$A$2:$A$6,0) -> 3 | L24: =MATCH(E24,'Rating Scale'!$A$2:$A$6,0) -> 2 | M24: =MATCH(F24,'Rating Scale'!$A$2:$A$6,0) -> 3 | N24: =MATCH(G24,'Rating Scale'!$A$2:$A$6,0) -> 2
A25: 21 | B25: =Evaluation!B102 -> Personal & Household Services | C25: =Evaluation!E102 -> Medium | D25: =Evaluation!E103 -> Medium | E25: =Evaluation!E104 -> Low | F25: =Evaluation!E105 -> Medium | G25: =Evaluation!E106 -> Medium | H25: =INDEX('Rating Scale'!$A$2:$A$6,MAX(ROUND(AVERAGE(J25:N25),0),MAX(J25:N25)-1)) -> Medium | J25: =MATCH(C25,'Rating Scale'!$A$2:$A$6,0) -> 2 | K25: =MATCH(D25,'Rating Scale'!$A$2:$A$6,0) -> 2 | L25: =MATCH(E25,'Rating Scale'!$A$2:$A$6,0) -> 1 | M25: =MATCH(F25,'Rating Scale'!$A$2:$A$6,0) -> 2 | N25: =MATCH(G25,'Rating Scale'!$A$2:$A$6,0) -> 2
A26: 22 | B26: =Evaluation!B107 -> Household Goods | C26: =Evaluation!E107 -> Medium | D26: =Evaluation!E108 -> Medium | E26: =Evaluation!E109 -> Medium | F26: =Evaluation!E110 -> Medium | G26: =Evaluation!E111 -> Low | H26: =INDEX('Rating Scale'!$A$2:$A$6,MAX(ROUND(AVERAGE(J26:N26),0),MAX(J26:N26)-1)) -> Medium | J26: =MATCH(C26,'Rating Scale'!$A$2:$A$6,0) -> 2 | K26: =MATCH(D26,'Rating Scale'!$A$2:$A$6,0) -> 2 | L26: =MATCH(E26,'Rating Scale'!$A$2:$A$6,0) -> 2 | M26: =MATCH(F26,'Rating Scale'!$A$2:$A$6,0) -> 2 | N26: =MATCH(G26,'Rating Scale'!$A$2:$A$6,0) -> 1
A27: 23 | B27: =Evaluation!B112 -> Business Services | C27: =Evaluation!E112 -> High | D27: =Evaluation!E113 -> Very High | E27: =Evaluation!E114 -> High | F27: =Evaluation!E115 -> Very High | G27: =Evaluation!E116 -> Medium | H27: =INDEX('Rating Scale'!$A$2:$A$6,MAX(ROUND(AVERAGE(J27:N27),0),MAX(J27:N27)-1)) -> High | J27: =MATCH(C27,'Rating Scale'!$A$2:$A$6,0) -> 3 | K27: =MATCH(D27,'Rating Scale'!$A$2:$A$6,0) -> 4 | L27: =MATCH(E27,'Rating Scale'!$A$2:$A$6,0) -> 3 | M27: =MATCH(F27,'Rating Scale'!$A$2:$A$6,0) -> 4 | N27: =MATCH(G27,'Rating Scale'!$A$2:$A$6,0) -> 2
B29: Distribution of ratings
B30: Rating | C30: Fraud | D30: Cyber / ICT | E30: Operational Resilience | F30: TPRM | G30: Governance / Operating Model | H30: Overall
B31: Critical | C31: =COUNTIF(C$5:C$27,$B31) -> 1 | D31: =COUNTIF(D$5:D$27,$B31) -> 3 | E31: =COUNTIF(E$5:E$27,$B31) -> 0 | F31: =COUNTIF(F$5:F$27,$B31) -> 0 | G31: =COUNTIF(G$5:G$27,$B31) -> 0 | H31: =COUNTIF(H$5:H$27,$B31) -> 0
B32: Very High | C32: =COUNTIF(C$5:C$27,$B32) -> 3 | D32: =COUNTIF(D$5:D$27,$B32) -> 6 | E32: =COUNTIF(E$5:E$27,$B32) -> 6 | F32: =COUNTIF(F$5:F$27,$B32) -> 8 | G32: =COUNTIF(G$5:G$27,$B32) -> 1 | H32: =COUNTIF(H$5:H$27,$B32) -> 5
B33: High | C33: =COUNTIF(C$5:C$27,$B33) -> 10 | D33: =COUNTIF(D$5:D$27,$B33) -> 8 | E33: =COUNTIF(E$5:E$27,$B33) -> 11 | F33: =COUNTIF(F$5:F$27,$B33) -> 11 | G33: =COUNTIF(G$5:G$27,$B33) -> 8 | H33: =COUNTIF(H$5:H$27,$B33) -> 13
B34: Medium | C34: =COUNTIF(C$5:C$27,$B34) -> 9 | D34: =COUNTIF(D$5:D$27,$B34) -> 6 | E34: =COUNTIF(E$5:E$27,$B34) -> 5 | F34: =COUNTIF(F$5:F$27,$B34) -> 4 | G34: =COUNTIF(G$5:G$27,$B34) -> 13 | H34: =COUNTIF(H$5:H$27,$B34) -> 5
B35: Low | C35: =COUNTIF(C$5:C$27,$B35) -> 0 | D35: =COUNTIF(D$5:D$27,$B35) -> 0 | E35: =COUNTIF(E$5:E$27,$B35) -> 1 | F35: =COUNTIF(F$5:F$27,$B35) -> 0 | G35: =COUNTIF(G$5:G$27,$B35) -> 1 | H35: =COUNTIF(H$5:H$27,$B35) -> 0
B36: Total | C36: =SUM(C31:C35) -> 23 | D36: =SUM(D31:D35) -> 23 | E36: =SUM(E31:E35) -> 23 | F36: =SUM(F31:F35) -> 23 | G36: =SUM(G31:G35) -> 23 | H36: =SUM(H31:H35) -> 23

Sheet Evaluation
A1: No. | B1: Sector / Scope | C1: Scope description | D1: Risk Area | E1: Rating | F1: Indicators and references | G1: Indicator count
A2: 1 | B2: Securitization – entire scope | C2: Originated, sponsored and invested ABS, RMBS, CLO, warehouse lines and SRT trades. | D2: Fraud | E2: Very High | F2: 1. Tricolor (Sept 2025): auto lender collapse amid alleged double-pledging of loan collateral across warehouse lenders 2. First Brands (Sept 2025): receivables and inventory allegedly financed more than once through off-balance-sheet SPVs 3. Collateral quality depends on originator loan tapes; loan-level misrepresentation usually surfaces only at default 4. Commingling of collections at servicer level creates diversion risk before cash reaches the SPV 5. Private and synthetic deals carry less public disclosure and fewer independent reviewers 6. Tighter credit cycle increases originators' incentive to misrepresent pool performance | G2: =LEN(F2)-LEN(SUBSTITUTE(F2,CHAR(10),""))+1 -> 6
A3: 1 | B3: Securitization – entire scope | C3: Originated, sponsored and invested ABS, RMBS, CLO, warehouse lines and SRT trades. | D3: Cyber / ICT | E3: Medium | F3: 1. Loan-level personal data held by servicers, trustees and securitisation repositories (GDPR scope) 2. Payment-diversion and BEC risk on waterfall payments and investor distributions 3. Ransomware at a servicer can halt collections and investor reporting 4. Bank's direct ICT exposure is limited; most risk sits with counterparties 5. Reporting runs through external ESMA-registered repositories and data platforms | G3: =LEN(F3)-LEN(SUBSTITUTE(F3,CHAR(10),""))+1 -> 5
A4: 1 | B4: Securitization – entire scope | C4: Originated, sponsored and invested ABS, RMBS, CLO, warehouse lines and SRT trades. | D4: Operational Resilience | E4: High | F4: 1. Single-servicer concentration; backup servicers are often 'cold' with no live data 2. Waterfall and cash-flow models frequently run in spreadsheets / end-user computing tools 3. Fixed investor-reporting deadlines (EU SR Art. 7) make processes time-critical 4. Collection continuity depends on the originator's own operations 5. Historical servicer transfers take months, exposing pools to performance drift | G4: =LEN(F4)-LEN(SUBSTITUTE(F4,CHAR(10),""))+1 -> 5
A5: 1 | B5: Securitization – entire scope | C5: Originated, sponsored and invested ABS, RMBS, CLO, warehouse lines and SRT trades. | D5: TPRM | E5: Very High | F5: 1. Long chain of parties: originator, servicer, trustee, cash manager, account bank, swap counterparty, rating agencies 2. Bank relies on originator reps, warranties and its own Art. 5 due diligence 3. Fourth-party exposure via servicers' outsourced IT and BPO providers 4. Limited audit rights over non-regulated originators (fintech, BNPL, specialty lenders) 5. Data-tape agreed-upon procedures are sample-based and miss systematic fraud | G5: =LEN(F5)-LEN(SUBSTITUTE(F5,CHAR(10),""))+1 -> 5
A6: 1 | B6: Securitization – entire scope | C6: Originated, sponsored and invested ABS, RMBS, CLO, warehouse lines and SRT trades. | D6: Governance / Operating Model | E6: High | F6: 1. Complex SPV structures relying on corporate service providers and independent directors 2. EU Securitisation Regulation and STS label carry administrative sanctions for breaches 3. SRT transactions require supervisory review of risk transfer and governance 4. Role conflicts when the bank is originator, sponsor, arranger and investor at once 5. Model and data ownership split across Front Office, Risk and Finance | G6: =LEN(F6)-LEN(SUBSTITUTE(F6,CHAR(10),""))+1 -> 5
A7: 2 | B7: Supply Chain facilities | C7: Reverse factoring, receivables purchase, payables finance and inventory finance programmes. | D7: Fraud | E7: Critical | F7: 1. Greensill Capital (2021): financing of prospective receivables and insurance gaps led to multi-billion losses for investors and lenders 2. First Brands Group (2025): alleged double-financing of invoices left factoring and SCF lenders with large unsecured exposure 3. Fictitious and duplicate invoices are the dominant fraud typology in receivables finance 4. Phantom or related-party buyers and invoice dilution are hard to detect at onboarding 5. Automated, same-day funding with limited invoice-level verification 6. Over- and under-invoicing are FATF trade-based money laundering red flags | G7: =LEN(F7)-LEN(SUBSTITUTE(F7,CHAR(10),""))+1 -> 6
A8: 2 | B8: Supply Chain facilities | C8: Reverse factoring, receivables purchase, payables finance and inventory finance programmes. | D8: Cyber / ICT | E8: High | F8: 1. Programmes run on multi-bank SCF platforms with API links into client ERPs 2. Supplier bank-detail changes are prime targets for business email compromise 3. High payment volumes to a long tail of small suppliers 4. Compromised supplier-portal credentials allow fake early-payment requests 5. Fintech platform partners show uneven security maturity | G8: =LEN(F8)-LEN(SUBSTITUTE(F8,CHAR(10),""))+1 -> 5
A9: 2 | B9: Supply Chain facilities | C9: Reverse factoring, receivables purchase, payables finance and inventory finance programmes. | D9: Operational Resilience | E9: High | F9: 1. Daily funding cycles: an outage stops supplier liquidity immediately 2. Dependence on platform availability and file transmission windows 3. Manual reconciliation of buyer repayments against funded invoices 4. Programmes concentrated on a few anchor buyers 5. Recovery plans rarely tested end to end with platforms | G9: =LEN(F9)-LEN(SUBSTITUTE(F9,CHAR(10),""))+1 -> 5
A10: 2 | B10: Supply Chain facilities | C10: Reverse factoring, receivables purchase, payables finance and inventory finance programmes. | D10: TPRM | E10: Very High | F10: 1. Third-party platforms perform supplier onboarding and hold invoice data 2. Credit insurance may not respond (Greensill / Tokio Marine coverage dispute) 3. Reliance on anchor buyer confirmation of invoices 4. Distribution to investors depends on the originating platform's controls 5. Thousands of suppliers onboarded with simplified KYC | G10: =LEN(F10)-LEN(SUBSTITUTE(F10,CHAR(10),""))+1 -> 5
A11: 2 | B11: Supply Chain facilities | C11: Reverse factoring, receivables purchase, payables finance and inventory finance programmes. | D11: Governance / Operating Model | E11: High | F11: 1. SCF often reported as trade payables rather than debt; IAS 7 / IFRS 7 supplier finance disclosures only effective from 2024 2. Product ownership spread across Trade, Cash Management and Credit 3. Buyer limits and supplier exposures can be set inconsistently 4. Rating agencies flag reverse factoring as 'hidden debt' 5. Fast programme growth outpaces control frameworks | G11: =LEN(F11)-LEN(SUBSTITUTE(F11,CHAR(10),""))+1 -> 5
A12: 3 | B12: Growth Solutions clients | C12: Scale-ups, venture-backed and high-growth mid-caps served by growth / innovation banking. | D12: Fraud | E12: High | F12: 1. Frank / JPMorgan (founder convicted 2025): fabricated customer numbers passed acquirer due diligence 2. Founder-led firms with weak segregation of duties 3. Pressure to inflate revenue or KPIs ahead of funding rounds 4. Short audit history; many first-time audits 5. Fast-changing business models hide anomalies in financials 6. Fintech, payments and BNPL models carry higher fraud loss rates | G12: =LEN(F12)-LEN(SUBSTITUTE(F12,CHAR(10),""))+1 -> 6
A13: 3 | B13: Growth Solutions clients | C13: Scale-ups, venture-backed and high-growth mid-caps served by growth / innovation banking. | D13: Cyber / ICT | E13: High | F13: 1. Small or outsourced security teams in cloud-first companies 2. SMEs and mid-market firms are heavily represented in ransomware cases (Verizon DBIR 2025) 3. SaaS sprawl without central identity and access governance 4. Frequent acquisitions and integrations open temporary gaps 5. Cyber insurance coverage often thin or absent | G13: =LEN(F13)-LEN(SUBSTITUTE(F13,CHAR(10),""))+1 -> 5
... A116: 23 | B116: Business Services | C116: BPO, outsourcing, consulting, staffing, payroll, facility management and professional services. | D116: Governance / Operating Model | E116: Medium | F116: 1. PE-owned roll-ups 2. Professional regulation (audit, legal) 3. Partnership structures 4. Conflicts of interest 5. Mature large providers | G116: =LEN(F116)-LEN(SUBSTITUTE(F116,CHAR(10),""))+1 -> 5

Sheet Rating Scale
A1: Rating | B1: Score | C1: Definition
A2: Low | B2: 1 | C2: Limited exposure; sector features rarely produce material loss; standard controls sufficient.
A3: Medium | B3: 2 | C3: Some exposure; events occur but impact is contained and substitutable; periodic monitoring.
A4: High | B4: 3 | C4: Recurring events with material loss potential; enhanced due diligence and KRIs warranted.
A5: Very High | B5: 4 | C5: Frequent or severe events in the sector; contagion to the bank plausible; senior oversight and specific limits.
A6: Critical | B6: 5 | C6: Systemic or recently crystallised large-scale losses; direct, fast contagion; top-priority deep-dive and risk appetite review.
A8: Overall rating rule: rounded mean of the five area scores, never more than one level below the highest area score (used in Heatmap column H).

Sheet Method & References
A1: Method and limits
A2: What is rated | B2: Inherent exposure of a typical client or transaction in each scope, before the bank's own mitigants (collateral, covenants, insurance, monitoring). It is a sector baseline for prioritising reviews, not a client-level rating.
A3: How ratings were set | B3: Each area weighs likelihood (threat activity, control maturity, regulatory signals) and impact (loss size, contagion to the bank, systemic reach). Indicators combine documented loss events, regulatory designations and structural features of the sector.
A4: Overall rating | B4: Rounded mean of the five area scores (Low = 1 to Critical = 5), never more than one level below the highest area score. A single Critical area lifts the overall to at least Very High.
A5: Calibrate before use | B5: Validate against internal loss data, KRIs, RCSA results, exposure size and client concentration. Event figures come from public reporting and court filings. Several 2025 cases (Tricolor, First Brands, Jaguar Land Rover, M&S) are still being litigated or investigated, so figures may be revised.
A7: Key references
A8: 1 | B8: EU Digital Operational Resilience Act (DORA), Regulation (EU) 2022/2554, and ESA designation of critical ICT third-party providers
A9: 2 | B9: NIS2 Directive (EU) 2022/2555: essential and important entity sectors
A10: 3 | B10: EBA Guidelines on outsourcing arrangements (EBA/GL/2019/02) and on internal governance (EBA/GL/2021/05)
A11: 4 | B11: Basel Committee, Principles for Operational Resilience (2021) and revised Principles for the Sound Management of Operational Risk
A12: 5 | B12: EU Securitisation Regulation (EU) 2017/2402: due diligence (Art. 5), transparency (Art. 7), STS criteria
A13: 6 | B13: IASB amendments to IAS 7 / IFRS 7 on supplier finance arrangements (effective 2024)
A14: 7 | B14: ACFE Occupational Fraud 2024: A Report to the Nations
A15: 8 | B15: IBM Cost of a Data Breach Report (2024, 2025); IBM X-Force Threat Intelligence Index
A16: 9 | B16: ENISA Threat Landscape (2024, 2025); Verizon Data Breach Investigations Report (2025)
A17: 10 | B17: CISA advisories on PRC state-sponsored activity (Volt Typhoon, Salt Typhoon), 2024-2025
A18: 11 | B18: CFCA Global Telecommunications Fraud Loss Survey (2023)
A19: 12 | B19: EPPO annual reports (VAT carousel / MTIC and agricultural subsidy fraud)
A20: 13 | B20: FATF guidance on trade-based money laundering and real estate sector risks
